{
    "incidentes": [
        {
            "incidentId": 2534,
            "userID": 8739,
            "userName": "Pablo Escobar",
            "data_": [
                [
                    {
                        "type": "Dropdown",
                        "title": "Tipodeincidente",
                        "value": "3",
                        "list": [
                            {
                                "title": "PlataformasdeTrabajo",
                                "value": 1
                            },
                            {
                                "title": "TrabajoDistintoNivel",
                                "value": 2
                            },
                            {
                                "title": "ManiobrasdeIzaje",
                                "value": 3
                            },
                            {
                                "title": "Excavaciones",
                                "value": 4
                            },
                            {
                                "title": "FaltaProteccióndeShaft,Vanos,Bordes",
                                "value": 5
                            },
                            {
                                "title": "TrabajosconMaquinariasyEquipos",
                                "value": 6
                            },
                            {
                                "title": "DescargayTrasladodeMaterial",
                                "value": 7
                            },
                            {
                                "title": "TrabajosEléctricos",
                                "value": 8
                            },
                            {
                                "title": "OrdenyAseo",
                                "value": 9
                            },
                            {
                                "title": "UsocorrectoEPP",
                                "value": 10
                            },
                            {
                                "title": "Otros",
                                "value": 11
                            }
                        ]
                    },
                    {
                        "type": "FechaHora",
                        "response": "17/3/2020-16:40"
                    },
                    {
                        "type": "Dropdown",
                        "title": "Responsable",
                        "value": "1",
                        "list": [
                            {
                                "title": "PabloEscobar",
                                "value": 1
                            },
                            {
                                "title": "CarlosGonzales",
                                "value": 2
                            },
                            {
                                "title": "EduardoReyes",
                                "value": 3
                            }
                        ]
                    },
                    {
                        "type": "Dropdown",
                        "title": "Faseconstructiva",
                        "value": "3",
                        "list": [
                            {
                                "title": "Obrasprevias",
                                "value": 1
                            },
                            {
                                "title": "Obragruesa",
                                "value": 2
                            },
                            {
                                "title": "Terminaciones",
                                "value": 3
                            },
                            {
                                "title": "Postventa",
                                "value": 6
                            }
                        ]
                    },
                    {
                        "type": "Dropdown",
                        "title": "Gravedad",
                        "value": "2",
                        "list": [
                            {
                                "title": "Alta",
                                "value": 1
                            },
                            {
                                "title": "Media",
                                "value": 2
                            },
                            {
                                "title": "Baja",
                                "value": 3
                            }
                        ]
                    },
                    {
                        "type": "TextArea",
                        "placeholder": "Descripción",
                        "response": "HayuntilproblemdeAltoriesgo"
                    }
                ]
            ]
        },
        {
            "incidentId": 2634,
            "userID": 8739,
            "userName": "Pablo Escobar",
            "data_": [
                [
                    {
                        "type": "Dropdown",
                        "title": "Tipodeincidente",
                        "value": "3",
                        "list": [
                            {
                                "title": "PlataformasdeTrabajo",
                                "value": 1
                            },
                            {
                                "title": "TrabajoDistintoNivel",
                                "value": 2
                            },
                            {
                                "title": "ManiobrasdeIzaje",
                                "value": 3
                            },
                            {
                                "title": "Excavaciones",
                                "value": 4
                            },
                            {
                                "title": "FaltaProteccióndeShaft,Vanos,Bordes",
                                "value": 5
                            },
                            {
                                "title": "TrabajosconMaquinariasyEquipos",
                                "value": 6
                            },
                            {
                                "title": "DescargayTrasladodeMaterial",
                                "value": 7
                            },
                            {
                                "title": "TrabajosEléctricos",
                                "value": 8
                            },
                            {
                                "title": "OrdenyAseo",
                                "value": 9
                            },
                            {
                                "title": "UsocorrectoEPP",
                                "value": 10
                            },
                            {
                                "title": "Otros",
                                "value": 11
                            }
                        ]
                    },
                    {
                        "type": "FechaHora",
                        "response": "17/3/2020-16:40"
                    },
                    {
                        "type": "Dropdown",
                        "title": "Responsable",
                        "value": "1",
                        "list": [
                            {
                                "title": "PabloEscobar",
                                "value": 1
                            },
                            {
                                "title": "CarlosGonzales",
                                "value": 2
                            },
                            {
                                "title": "EduardoReyes",
                                "value": 3
                            }
                        ]
                    },
                    {
                        "type": "Dropdown",
                        "title": "Faseconstructiva",
                        "value": "3",
                        "list": [
                            {
                                "title": "Obrasprevias",
                                "value": 1
                            },
                            {
                                "title": "Obragruesa",
                                "value": 2
                            },
                            {
                                "title": "Terminaciones",
                                "value": 3
                            },
                            {
                                "title": "Postventa",
                                "value": 6
                            }
                        ]
                    },
                    {
                        "type": "Dropdown",
                        "title": "Gravedad",
                        "value": "2",
                        "list": [
                            {
                                "title": "Alta",
                                "value": 1
                            },
                            {
                                "title": "Media",
                                "value": 2
                            },
                            {
                                "title": "Baja",
                                "value": 3
                            }
                        ]
                    },
                    {
                        "type": "TextArea",
                        "placeholder": "Descripción",
                        "response": "HayuntilproblemdeAltoriesgo"
                    }
                ]
            ]
        }                 
    ]
}